{
    "name": "Zenith Twilight",
    "variant": "twilight",
    "type": "dark",
    "description": "A deeper, moodier variant for those late-night coding sessions",
    "author": "samonide",
    "version": "3.0.0",
    "colors": {
        "base": {
            "bg": "#1d1d28",
            "bgAlt": "#252532",
            "bgHighlight": "#2d2d3c",
            "bgVisual": "#353548",
            "bgSidebar": "#191922",
            "fg": "#c8c5d8",
            "fgAlt": "#a09bb6",
            "fgDark": "#706b88"
        },
        "syntax": {
            "blue": "#7d98f5",
            "cyan": "#68bde0",
            "green": "#8dd588",
            "purple": "#bd96f5",
            "orange": "#f5af72",
            "red": "#f58899",
            "yellow": "#f2dca8",
            "pink": "#f592c0",
            "lavender": "#b3a6f0",
            "peach": "#f5a886",
            "mint": "#88dcb0",
            "sky": "#7db5cc"
        },
        "ui": {
            "border": "#323240",
            "comment": "#757090",
            "selection": "#2a2a3a",
            "cursorLine": "#212128"
        },
        "git": {
            "add": "#7fd97f",
            "change": "#f9e2af",
            "delete": "#ff7b9c"
        },
        "diagnostic": {
            "error": "#ff7b9c",
            "warning": "#f9e2af",
            "info": "#6d8fff",
            "hint": "#4fc1e9"
        }
    },
    "mapping": {
        "keywords": "lavender",
        "types": "sky",
        "strings": "green",
        "variables": "purple",
        "constants": "orange",
        "functions": "blue",
        "comments": "comment",
        "operators": "cyan",
        "numbers": "orange"
    }
}